odoo/addons/ddmrp_product_replace/README.rst
odoo/addons/ddmrp_product_replace/__init__.py
odoo/addons/ddmrp_product_replace/__manifest__.py
odoo/addons/ddmrp_product_replace/i18n/ddmrp_product_replace.pot
odoo/addons/ddmrp_product_replace/models/__init__.py
odoo/addons/ddmrp_product_replace/models/stock_warehouse_orderpoint.py
odoo/addons/ddmrp_product_replace/readme/CONTRIBUTORS.rst
odoo/addons/ddmrp_product_replace/readme/CREDITS.rst
odoo/addons/ddmrp_product_replace/readme/DESCRIPTION.rst
odoo/addons/ddmrp_product_replace/readme/ROADMAP.rst
odoo/addons/ddmrp_product_replace/readme/USAGE.rst
odoo/addons/ddmrp_product_replace/static/description/icon.png
odoo/addons/ddmrp_product_replace/static/description/index.html
odoo/addons/ddmrp_product_replace/tests/__init__.py
odoo/addons/ddmrp_product_replace/tests/test_product_replace.py
odoo/addons/ddmrp_product_replace/views/stock_warehouse_orderpoint_view.xml
odoo/addons/ddmrp_product_replace/wizards/__init__.py
odoo/addons/ddmrp_product_replace/wizards/ddmrp_product_replace.py
odoo/addons/ddmrp_product_replace/wizards/ddmrp_product_replace_view.xml
odoo11_addon_ddmrp_product_replace-11.0.1.0.1.99.dev5.dist-info/METADATA
odoo11_addon_ddmrp_product_replace-11.0.1.0.1.99.dev5.dist-info/WHEEL
odoo11_addon_ddmrp_product_replace-11.0.1.0.1.99.dev5.dist-info/top_level.txt
odoo11_addon_ddmrp_product_replace-11.0.1.0.1.99.dev5.dist-info/RECORD
